Metadata-Version: 1.0
Name: tokenbucket
Version: 1.1.1
Summary: UNKNOWN
Home-page: http://sendapatch.se/
Author: Ludvig Ericson
Author-email: ludvig@lericson.se
License: UNKNOWN
Platform: UNKNOWN
